Tower_defence_Golear_Karpenko/__init__.py
Tower_defence_Golear_Karpenko/__main__.py
Tower_defence_Golear_Karpenko/config.py
Tower_defence_Golear_Karpenko/assets/images/block.png
Tower_defence_Golear_Karpenko/assets/images/empty.png
Tower_defence_Golear_Karpenko/assets/images/enemy.png
Tower_defence_Golear_Karpenko/assets/images/grass.png
Tower_defence_Golear_Karpenko/assets/images/road.png
Tower_defence_Golear_Karpenko/assets/images/buttons/nextWave.png
Tower_defence_Golear_Karpenko/assets/images/buttons/play.png
Tower_defence_Golear_Karpenko/assets/images/buttons/quit.png
Tower_defence_Golear_Karpenko/assets/images/towers/tower1.png
Tower_defence_Golear_Karpenko/assets/images/towers/tower2.png
Tower_defence_Golear_Karpenko/assets/images/towers/tower3.png
Tower_defence_Golear_Karpenko/assets/sounds/background.ogg
Tower_defence_Golear_Karpenko/assets/towers/tower.txt
Tower_defence_Golear_Karpenko/assets/worlds/world1.txt
Tower_defence_Golear_Karpenko/assets/worlds/world2.txt
Tower_defence_Golear_Karpenko/base_classes/__init__.py
Tower_defence_Golear_Karpenko/base_classes/coordinate.py
Tower_defence_Golear_Karpenko/base_classes/game.py
Tower_defence_Golear_Karpenko/base_classes/menu.py
Tower_defence_Golear_Karpenko/base_classes/rectangle.py
Tower_defence_Golear_Karpenko/base_classes/sprite.py
Tower_defence_Golear_Karpenko/base_classes/world.py
Tower_defence_Golear_Karpenko/entity/__init__.py
Tower_defence_Golear_Karpenko/entity/bullet.py
Tower_defence_Golear_Karpenko/entity/button.py
Tower_defence_Golear_Karpenko/entity/enemy.py
Tower_defence_Golear_Karpenko/entity/tower.py
Tower_defence_Golear_Karpenko/entity_controller/__init__.py
Tower_defence_Golear_Karpenko/entity_controller/customer.py
Tower_defence_Golear_Karpenko/entity_controller/enemy_controller.py
Tower_defence_Golear_Karpenko/entity_controller/tower_builder.py
Tower_defence_Golear_Karpenko/misc/__init__.py
Tower_defence_Golear_Karpenko/misc/fps_counter.py
Tower_defence_Golear_Karpenko-0.2.9.dist-info/LICENSE.txt
Tower_defence_Golear_Karpenko-0.2.9.dist-info/METADATA
Tower_defence_Golear_Karpenko-0.2.9.dist-info/WHEEL
Tower_defence_Golear_Karpenko-0.2.9.dist-info/entry_points.txt
Tower_defence_Golear_Karpenko-0.2.9.dist-info/top_level.txt
Tower_defence_Golear_Karpenko-0.2.9.dist-info/RECORD
