Metadata-Version: 2.1
Name: Tower-defence-Golear-Karpenko
Version: 0.2.9
Summary: Simple tower defence game built on PyGame
Home-page: UNKNOWN
Author: Golear_Karpenko
Author-email: golyar.d@gmail.com
License: UNKNOWN
Platform: UNKNOWN
Classifier: Programming Language :: Python :: 3
Classifier: License :: OSI Approved :: MIT License
Classifier: Operating System :: OS Independent
Classifier: Development Status :: 3 - Alpha
Requires-Dist: pygame
